evosphere/__init__.py
evosphere/api/__init__.py
evosphere/api/server.py
evosphere/assimilation/__init__.py
evosphere/assimilation/data_assimilator.py
evosphere/assimilation/data_fusion.py
evosphere/assimilation/real_time_updater.py
evosphere/assimilation/uncertainty_quantification.py
evosphere/cli/__init__.py
evosphere/cli/main.py
evosphere/cli/server.py
evosphere/compiler/__init__.py
evosphere/compiler/bytecode.py
evosphere/compiler/compiler.py
evosphere/compiler/language.py
evosphere/core/__init__.py
evosphere/core/engine.py
evosphere/core/graph_network.py
evosphere/core/quantum_simulator.py
evosphere/coupling/__init__.py
evosphere/coupling/coupling_engine.py
evosphere/coupling/emergence_detector.py
evosphere/coupling/feedback_controller.py
evosphere/coupling/multi_scale_integrator.py
evosphere/designer/__init__.py
evosphere/designer/constraint_engine.py
evosphere/designer/optimization_engine.py
evosphere/designer/pathway_designer.py
evosphere/graph/__init__.py
evosphere/graph/adaptive_graph.py
evosphere/graph/graph_layers.py
evosphere/graph/temporal_dynamics.py
evosphere/quantum/__init__.py
evosphere/quantum/operators.py
evosphere/quantum/quantum_engine.py
evosphere/quantum/state_space.py
evosphere/quantum/utils.py
evosphere-1.0.0.dist-info/METADATA
evosphere-1.0.0.dist-info/WHEEL
evosphere-1.0.0.dist-info/entry_points.txt
evosphere-1.0.0.dist-info/top_level.txt
evosphere-1.0.0.dist-info/RECORD
