Metadata-Version: 2.4
Name: evosphere
Version: 1.0.0
Summary: The Evolutionary Bio-Compiler: A living engine for programming biology through evolution itself
Author-email: Krishna Bajpai <krishna@krishnabajpai.me>, Vedanshi Gupta <vedanshigupta158@gmail.com>
License: MIT
Project-URL: Homepage, https://github.com/krishnabajpai/evosphere
Project-URL: Documentation, https://evosphere.readthedocs.io
Project-URL: Repository, https://github.com/krishnabajpai/evosphere.git
Project-URL: Bug Tracker, https://github.com/krishnabajpai/evosphere/issues
Keywords: bioinformatics,evolution,quantum-computing,genomics,machine-learning
Classifier: Development Status :: 4 - Beta
Classifier: Intended Audience :: Science/Research
Classifier: License :: OSI Approved :: MIT License
Classifier: Operating System :: OS Independent
Classifier: Programming Language :: Python :: 3
Classifier: Programming Language :: Python :: 3.9
Classifier: Programming Language :: Python :: 3.10
Classifier: Programming Language :: Python :: 3.11
Classifier: Programming Language :: Python :: 3.12
Classifier: Topic :: Scientific/Engineering :: Bio-Informatics
Classifier: Topic :: Scientific/Engineering :: Artificial Intelligence
Requires-Python: >=3.9
Requires-Dist: numpy>=1.24.0
Requires-Dist: scipy>=1.10.0
Requires-Dist: pandas>=2.0.0
Requires-Dist: networkx>=3.0
Requires-Dist: scikit-learn>=1.3.0
Requires-Dist: torch>=2.0.0
Requires-Dist: torch-geometric>=2.3.0
Requires-Dist: qiskit>=0.45.0
Requires-Dist: qiskit-aer>=0.12.0
Requires-Dist: biopython>=1.81
Requires-Dist: plotly>=5.15.0
Requires-Dist: dash>=2.14.0
Requires-Dist: fastapi>=0.100.0
Requires-Dist: uvicorn>=0.23.0
Requires-Dist: pydantic>=2.0.0
Requires-Dist: click>=8.1.0
Requires-Dist: rich>=13.0.0
Requires-Dist: tqdm>=4.65.0
Requires-Dist: h5py>=3.9.0
Requires-Dist: zarr>=2.15.0
Requires-Dist: numba>=0.57.0
Requires-Dist: jax[cpu]>=0.4.13
Requires-Dist: optax>=0.1.7
Requires-Dist: gymnasium>=0.29.0
Requires-Dist: stable-baselines3>=2.0.0
Requires-Dist: pyvcf3>=1.0.3
Requires-Dist: pysam>=0.21.0
Requires-Dist: matplotlib>=3.7.0
Provides-Extra: quantum
Requires-Dist: qiskit-optimization>=0.6.0; extra == "quantum"
Requires-Dist: qiskit-machine-learning>=0.7.0; extra == "quantum"
Requires-Dist: pennylane>=0.32.0; extra == "quantum"
Requires-Dist: cirq>=1.2.0; extra == "quantum"
Provides-Extra: server
Requires-Dist: fastapi>=0.100.0; extra == "server"
Requires-Dist: uvicorn[standard]>=0.23.0; extra == "server"
Requires-Dist: gunicorn>=21.0.0; extra == "server"
Requires-Dist: websockets>=11.0.0; extra == "server"
Requires-Dist: aiofiles>=23.0.0; extra == "server"
Requires-Dist: python-multipart>=0.0.6; extra == "server"
Provides-Extra: cuda
Requires-Dist: cupy>=12.0.0; extra == "cuda"
Requires-Dist: torch[cuda]>=2.0.0; extra == "cuda"
Provides-Extra: docs
Requires-Dist: mkdocs>=1.5.0; extra == "docs"
Requires-Dist: mkdocs-material>=9.2.0; extra == "docs"
Requires-Dist: mkdocstrings[python]>=0.22.0; extra == "docs"
Requires-Dist: mkdocs-jupyter>=0.24.0; extra == "docs"
Provides-Extra: test
Requires-Dist: pytest>=7.4.0; extra == "test"
Requires-Dist: pytest-cov>=4.1.0; extra == "test"
Requires-Dist: pytest-mock>=3.11.0; extra == "test"
Requires-Dist: pytest-asyncio>=0.21.0; extra == "test"
Requires-Dist: hypothesis>=6.82.0; extra == "test"
Provides-Extra: dev
Requires-Dist: black>=23.7.0; extra == "dev"
Requires-Dist: isort>=5.12.0; extra == "dev"
Requires-Dist: flake8>=6.0.0; extra == "dev"
Requires-Dist: mypy>=1.5.0; extra == "dev"
Requires-Dist: pre-commit>=3.3.0; extra == "dev"
